verysimpletree/.coverage
verysimpletree/__init__.py
verysimpletree/py.typed
verysimpletree/test_tree.py
verysimpletree/tree.py
verysimpletree/util.py
verysimpletree-1.2.1.dist-info/METADATA
verysimpletree-1.2.1.dist-info/WHEEL
verysimpletree-1.2.1.dist-info/RECORD
